<?xml version="1.0" encoding="UTF-8"?>
<?xml-stylesheet type="text/xsl" href="default.xsl"?>
<fr:tree
xmlns:fr="http://www.jonmsterling.com/jms-005P.xml"
toc="true"
numbered="true"
show-heading="true"
show-metadata="true"
expanded="true"
root="false"><fr:frontmatter><fr:anchor>1511</fr:anchor><fr:taxon>Equation</fr:taxon><fr:addr>hodge-theory-ii-3.2.8.1</fr:addr><fr:route>hodge-theory-ii-3.2.8.1.xml</fr:route><fr:number>3.2.8.1</fr:number><fr:parent>hodge-theory-ii-3.2.8</fr:parent></fr:frontmatter><fr:mainmatter><fr:tex
display="block">           d_1 \colon             \operatorname {H} ^{k-n}( \widetilde {Y}^n, \varepsilon ^n)            \to   \operatorname {H} ^{k-n+1}( \widetilde {Y}^{n-1}, \varepsilon ^{n-1})         \tag{3.2.8.1}         </fr:tex></fr:mainmatter><fr:backmatter><fr:contributions></fr:contributions><fr:context><fr:tree
xmlns:fr="http://www.jonmsterling.com/jms-005P.xml"
toc="true"
numbered="false"
show-heading="true"
show-metadata="true"
expanded="true"
root="false"><fr:frontmatter><fr:anchor>1510</fr:anchor><fr:taxon>Lemma</fr:taxon><fr:addr>hodge-theory-ii-3.2.8</fr:addr><fr:route>hodge-theory-ii-3.2.8.xml</fr:route><fr:number>3.2.8</fr:number><fr:parent>hodge-theory-ii-3.2</fr:parent></fr:frontmatter><fr:mainmatter><fr:p>
    The differentials <fr:tex>d_1</fr:tex> of the spectral sequence <fr:tex>{}_WE</fr:tex> are strictly compatible with the filtration <fr:tex>F</fr:tex>.
  </fr:p>
  
    
    <fr:tree
xmlns:fr="http://www.jonmsterling.com/jms-005P.xml"
toc="false"
numbered="false"
show-heading="true"
show-metadata="false"
expanded="true"
root="false"><fr:frontmatter><fr:anchor>500</fr:anchor><fr:taxon>Proof</fr:taxon><fr:parent>hodge-theory-ii-3.2.8</fr:parent></fr:frontmatter><fr:mainmatter>
    <fr:p>
      On the <fr:tex>E_1</fr:tex> pages, there is only the filtration induced by <fr:tex>F</fr:tex> to consider (<fr:ref
addr="hodge-theory-ii-1.3.10"
href="hodge-theory-ii-1.3.10.xml"
taxon="Lemma"
number="1.3.10"></fr:ref> and (iii) of <fr:ref
addr="hodge-theory-ii-1.3.13"
href="hodge-theory-ii-1.3.13.xml"
taxon="Proposition"
number="1.3.13"></fr:ref>), and <fr:tex>d_1</fr:tex> is compatible with this filtration ((i) of <fr:ref
addr="hodge-theory-ii-1.3.13"
href="hodge-theory-ii-1.3.13.xml"
taxon="Proposition"
number="1.3.13"></fr:ref>).
      This filtration is the abutment of the spectral sequence in <fr:ref
addr="hodge-theory-ii-3.2.6"
href="hodge-theory-ii-3.2.6.xml"
taxon="Lemma"
number="3.2.6"></fr:ref> ((ii) of <fr:ref
addr="hodge-theory-ii-1.4.8"
href="hodge-theory-ii-1.4.8.xml"
taxon="Example"
number="1.4.8"></fr:ref>).
      By <fr:ref
addr="hodge-theory-ii-3.2.7"
href="hodge-theory-ii-3.2.7.xml"
taxon="Lemma"
number="3.2.7"></fr:ref>, the arrow
      <fr:tex
display="block">         d_1 \colon           \operatorname { \mathbb {H}} ^k( \bar {X}, \operatorname {Gr} _n^W( \Omega _{ \bar {X}}^ \bullet \langle  Y \rangle ))          \to   \operatorname { \mathbb {H}} ^{k+1}( \bar {X}, \operatorname {Gr} _{n-1}^W( \Omega _{ \bar {X}}^ \bullet \langle  Y \rangle ))       </fr:tex>
      or

      <fr:tree
xmlns:fr="http://www.jonmsterling.com/jms-005P.xml"
toc="true"
numbered="false"
show-heading="true"
show-metadata="false"
expanded="true"
root="false"><fr:frontmatter><fr:anchor>499</fr:anchor><fr:taxon>Equation</fr:taxon><fr:addr>hodge-theory-ii-3.2.8.1</fr:addr><fr:route>hodge-theory-ii-3.2.8.1.xml</fr:route><fr:number>3.2.8.1</fr:number><fr:parent>hodge-theory-ii-3.2.8</fr:parent></fr:frontmatter><fr:mainmatter><fr:tex
display="block">           d_1 \colon             \operatorname {H} ^{k-n}( \widetilde {Y}^n, \varepsilon ^n)            \to   \operatorname {H} ^{k-n+1}( \widetilde {Y}^{n-1}, \varepsilon ^{n-1})         \tag{3.2.8.1}         </fr:tex></fr:mainmatter></fr:tree>

      is compatible with the filtrations that are <fr:tex>(k+n)</fr:tex>-opposite to their complex conjugate.
      Since <fr:tex>d_1</fr:tex> commutes up to complex conjugation, <fr:tex>d_1</fr:tex> respects the bigrading (of weight <fr:tex>k+n</fr:tex>) defined by <fr:tex>F</fr:tex> and <fr:tex>\bar {F}</fr:tex>, which proves <fr:ref
addr="hodge-theory-ii-3.2.8"
href="hodge-theory-ii-3.2.8.xml"
taxon="Lemma"
number="3.2.8"></fr:ref>.
    </fr:p>
  </fr:mainmatter></fr:tree>
  
</fr:mainmatter></fr:tree></fr:context><fr:related></fr:related><fr:backlinks></fr:backlinks><fr:references></fr:references></fr:backmatter></fr:tree>