<?xml version="1.0" encoding="UTF-8"?>
<?xml-stylesheet type="text/xsl" href="default.xsl"?>
<fr:tree
xmlns:fr="http://www.jonmsterling.com/jms-005P.xml"
toc="true"
numbered="true"
show-heading="true"
show-metadata="true"
expanded="true"
root="false"><fr:frontmatter><fr:anchor>2476</fr:anchor><fr:taxon>Proof</fr:taxon><fr:addr>#192</fr:addr><fr:route>unstable-192.xml</fr:route><fr:parent>hodge-theory-ii-4.2.10</fr:parent></fr:frontmatter><fr:mainmatter>
    <fr:p>
      Let <fr:tex>G</fr:tex>, <fr:tex>G'</fr:tex>, and <fr:tex>G''</fr:tex> be the groups defined by <fr:tex>V</fr:tex>, <fr:tex>V'</fr:tex>, and <fr:tex>V''</fr:tex>, respectively.
      Then <fr:tex>V'</fr:tex> is stable under <fr:tex>G</fr:tex>, just as it is under <fr:tex>\pi </fr:tex>, whence a morphism
      <fr:tex
display="block">         u         = (u',u'')\colon  G\to  G'\times  G''       </fr:tex>
      with unipotent kernel, and such that <fr:tex>u'</fr:tex> and <fr:tex>u''</fr:tex> are surjective.
      Let <fr:tex>N</fr:tex> be the identity component of the kernel of <fr:tex>u''</fr:tex>.
      Since <fr:tex>u'</fr:tex> is surjective, <fr:tex>u'(N)</fr:tex> is distinguished in <fr:tex>G'</fr:tex>, and thus does not admit any quotient of multiplicative type.
      
      If <fr:tex>\chi </fr:tex> is a character of <fr:tex>G^0</fr:tex>, then <fr:tex>\chi </fr:tex> factors through <fr:tex>u(G^0)</fr:tex> and vanishes on <fr:tex>N</fr:tex>;
      then a power of <fr:tex>\chi </fr:tex> factors through <fr:tex>{G''}^0</fr:tex>, and so <fr:tex>\chi </fr:tex> is trivial.
    </fr:p>
  </fr:mainmatter><fr:backmatter><fr:contributions></fr:contributions><fr:context><fr:tree
xmlns:fr="http://www.jonmsterling.com/jms-005P.xml"
toc="true"
numbered="false"
show-heading="true"
show-metadata="true"
expanded="true"
root="false"><fr:frontmatter><fr:anchor>2475</fr:anchor><fr:taxon>Lemma</fr:taxon><fr:addr>hodge-theory-ii-4.2.10</fr:addr><fr:route>hodge-theory-ii-4.2.10.xml</fr:route><fr:number>4.2.10</fr:number><fr:parent>hodge-theory-ii-4.2</fr:parent></fr:frontmatter><fr:mainmatter><fr:p>
    Let <fr:tex>0\to  V'\to  V\to  V''\to 0</fr:tex> be an exact sequence of representations of the above type.
    Then <fr:tex>V</fr:tex> satisfies <fr:ref
addr="hodge-theory-ii-4.2.star"
href="hodge-theory-ii-4.2.star.xml"
taxon="Property"
number="*"></fr:ref> if (and only if) <fr:tex>V'</fr:tex> and <fr:tex>V''</fr:tex> satisfy <fr:ref
addr="hodge-theory-ii-4.2.star"
href="hodge-theory-ii-4.2.star.xml"
taxon="Property"
number="*"></fr:ref>.
  </fr:p>
  
    
    <fr:tree
xmlns:fr="http://www.jonmsterling.com/jms-005P.xml"
toc="false"
numbered="false"
show-heading="true"
show-metadata="false"
expanded="true"
root="false"><fr:frontmatter><fr:anchor>1192</fr:anchor><fr:taxon>Proof</fr:taxon><fr:addr>#192</fr:addr><fr:route>unstable-192.xml</fr:route><fr:parent>hodge-theory-ii-4.2.10</fr:parent></fr:frontmatter><fr:mainmatter>
    <fr:p>
      Let <fr:tex>G</fr:tex>, <fr:tex>G'</fr:tex>, and <fr:tex>G''</fr:tex> be the groups defined by <fr:tex>V</fr:tex>, <fr:tex>V'</fr:tex>, and <fr:tex>V''</fr:tex>, respectively.
      Then <fr:tex>V'</fr:tex> is stable under <fr:tex>G</fr:tex>, just as it is under <fr:tex>\pi </fr:tex>, whence a morphism
      <fr:tex
display="block">         u         = (u',u'')\colon  G\to  G'\times  G''       </fr:tex>
      with unipotent kernel, and such that <fr:tex>u'</fr:tex> and <fr:tex>u''</fr:tex> are surjective.
      Let <fr:tex>N</fr:tex> be the identity component of the kernel of <fr:tex>u''</fr:tex>.
      Since <fr:tex>u'</fr:tex> is surjective, <fr:tex>u'(N)</fr:tex> is distinguished in <fr:tex>G'</fr:tex>, and thus does not admit any quotient of multiplicative type.
      
      If <fr:tex>\chi </fr:tex> is a character of <fr:tex>G^0</fr:tex>, then <fr:tex>\chi </fr:tex> factors through <fr:tex>u(G^0)</fr:tex> and vanishes on <fr:tex>N</fr:tex>;
      then a power of <fr:tex>\chi </fr:tex> factors through <fr:tex>{G''}^0</fr:tex>, and so <fr:tex>\chi </fr:tex> is trivial.
    </fr:p>
  </fr:mainmatter></fr:tree>
  
</fr:mainmatter></fr:tree></fr:context><fr:related></fr:related><fr:backlinks></fr:backlinks><fr:references></fr:references></fr:backmatter></fr:tree>